task.v
`timescale 1ns/1ps

module divider_8bit (
    input wire clk,
    input wire rst,                 // synchronous reset
    input wire start,               // start signal
    input wire [7:0] dividend,
    input wire [7:0] divisor,
    output reg [7:0] quotient,
    output reg [7:0] remainder,
    output reg ready
);

    reg [15:0] rem_reg;             // 16-bit remainder register
    reg [7:0] div_reg;              // divisor register
    reg [3:0] count;                // 0 to 8 (needs 4 bits)
    reg busy;

    always @(posedge clk) begin
        if (rst) begin
            quotient  <= 0;
            remainder <= 0;
            rem_reg   <= 0;
            div_reg   <= 0;
            count     <= 0;
            ready     <= 0;
            busy      <= 0;
        end

        else begin

            // START CONDITION
            if (start && !busy) begin
                ready    <= 0;
                busy     <= 1;
                count    <= 0;
                quotient <= dividend;
                div_reg  <= divisor;
                rem_reg  <= 0;

                // divide by zero protection
                if (divisor == 0) begin
                    quotient  <= 8'hFF;
                    remainder <= dividend;
                    ready     <= 1;
                    busy      <= 0;
                end
            end

            // DIVISION PROCESS (8 iterations)
            else if (busy) begin
                if (count < 8) begin

                    // Left shift {remainder, quotient}
                    rem_reg = {rem_reg[14:0], quotient[7]};
                    quotient = {quotient[6:0], 1'b0};

                    // Subtract divisor
                    rem_reg = rem_reg - {8'b0, div_reg};

                    if (rem_reg[15] == 1) begin
                        // Negative -> restore
                        rem_reg = rem_reg + {8'b0, div_reg};
                        quotient[0] = 0;
                    end
                    else begin
                        quotient[0] = 1;
                    end

                    count <= count + 1;
                end
                else begin
                    // DONE (after 8 cycles)
                    remainder <= rem_reg[7:0];
                    ready <= 1;
                    busy  <= 0;
                end
            end
        end
    end

endmodule

task_tb.v
`timescale 1ns/1ps

module tb_divider;

    reg clk;
    reg rst;
    reg start;
    reg [7:0] dividend;
    reg [7:0] divisor;

    wire [7:0] quotient;
    wire [7:0] remainder;
    wire ready;

    // Instantiate Divider
    divider_8bit uut (
        .clk(clk),
        .rst(rst),
        .start(start),
        .dividend(dividend),
        .divisor(divisor),
        .quotient(quotient),
        .remainder(remainder),
        .ready(ready)
    );

    // Clock generation (10ns period)
    always #5 clk = ~clk;

    initial begin
        $dumpfile("divider.vcd");
        $dumpvars(0, tb_divider);

        clk = 0;
        rst = 1;
        start = 0;
        dividend = 0;
        divisor = 0;

        #20;
        rst = 0;

        // Test Case 1: 100 / 7
        #10;
        dividend = 8'd100;
        divisor  = 8'd7;
        start = 1;
        #10;
        start = 0;

        wait(ready);
        #10;

        // Test Case 2: 55 / 5
        dividend = 8'd55;
        divisor  = 8'd5;
        start = 1;
        #10;
        start = 0;

        wait(ready);
        #10;

        // Test Case 3: Divide by zero
        dividend = 8'd25;
        divisor  = 8'd0;
        start = 1;
        #10;
        start = 0;

        wait(ready);
        #20;

        $finish;
    end

endmodule

divider.vcd
$date
	Fri Feb 27 09:46:10 2026
$end
$version
	Icarus Verilog
$end
$timescale
	1ps
$end
$scope module tb_divider $end
$var wire 8 ! remainder [7:0] $end
$var wire 1 " ready $end
$var wire 8 # quotient [7:0] $end
$var reg 1 $ clk $end
$var reg 8 % dividend [7:0] $end
$var reg 8 & divisor [7:0] $end
$var reg 1 ' rst $end
$var reg 1 ( start $end
$scope module uut $end
$var wire 1 $ clk $end
$var wire 8 ) dividend [7:0] $end
$var wire 8 * divisor [7:0] $end
$var wire 1 ' rst $end
$var wire 1 ( start $end
$var reg 1 + busy $end
$var reg 4 , count [3:0] $end
$var reg 8 - div_reg [7:0] $end
$var reg 8 . quotient [7:0] $end
$var reg 1 " ready $end
$var reg 16 / rem_reg [15:0] $end
$var reg 8 0 remainder [7:0] $end
$upscope $end
$upscope $end
$enddefinitions $end
#0
$dumpvars
bx 0
bx /
bx .
bx -
bx ,
x+
b0 *
b0 )
0(
1'
b0 &
b0 %
0$
bx #
x"
bx !
$end
#5000
0+
0"
b0 ,
b0 -
b0 /
b0 !
b0 0
b0 #
b0 .
1$
#10000
0$
#15000
1$
#20000
0$
0'
#25000
1$
#30000
0$
1(
b111 &
b111 *
b1100100 %
b1100100 )
#35000
b111 -
b1100100 #
b1100100 .
1+
1$
#40000
0$
0(
#45000
b1 ,
b0 /
b11001000 #
b11001000 .
1$
#50000
0$
#55000
b10 ,
b10010000 #
b10010000 .
b1 /
1$
#60000
0$
#65000
b11 ,
b100000 #
b100000 .
b11 /
1$
#70000
0$
#75000
b100 ,
b1000000 #
b1000000 .
b110 /
1$
#80000
0$
#85000
b101 ,
b10000001 #
b10000001 .
b101 /
1$
#90000
0$
#95000
b110 ,
b11 #
b11 .
b100 /
1$
#100000
0$
#105000
b111 ,
b111 #
b111 .
b1 /
1$
#110000
0$
#115000
b1000 ,
b1110 #
b1110 .
b10 /
1$
#120000
0$
#125000
0+
1"
b10 !
b10 0
1$
#130000
0$
#135000
b0 /
b101 -
b110111 #
b110111 .
b0 ,
1+
0"
1$
1(
b101 &
b101 *
b110111 %
b110111 )
#140000
0$
#145000
b1 ,
b0 /
b1101110 #
b1101110 .
1$
0(
#150000
0$
#155000
b10 ,
b0 /
b11011100 #
b11011100 .
1$
#160000
0$
#165000
b11 ,
b10111000 #
b10111000 .
b1 /
1$
#170000
0$
#175000
b100 ,
b1110000 #
b1110000 .
b11 /
1$
#180000
0$
#185000
b101 ,
b11100001 #
b11100001 .
b1 /
1$
#190000
0$
#195000
b110 ,
b11000010 #
b11000010 .
b11 /
1$
#200000
0$
#205000
b111 ,
b10000101 #
b10000101 .
b10 /
1$
#210000
0$
#215000
b1000 ,
b1011 #
b1011 .
b0 /
1$
#220000
0$
#225000
0+
1"
b0 !
b0 0
1$
#230000
0$
#235000
b11001 !
b11001 0
b0 -
b11111111 #
b11111111 .
b0 ,
0+
1"
1$
1(
b0 &
b0 *
b11001 %
b11001 )
#240000
0$
#245000
1$
0(
