task3.v
module mul8u_fast (
    input  [7:0] a,
    input  [7:0] b,
    output [15:0] y
);

    wire [15:0] pp [7:0];

    genvar i;
    generate
        for (i = 0; i < 8; i = i + 1) begin : PARTIALS
            assign pp[i] = b[i] ? (a << i) : 16'b0;
        end
    endgenerate

    assign y = pp[0] + pp[1] + pp[2] + pp[3]
             + pp[4] + pp[5] + pp[6] + pp[7];

endmodule

task3_tb.v
module tb_mul8u_fast;

    reg  [7:0] a, b;
    wire [15:0] y;

    mul8u_fast DUT (.a(a), .b(b), .y(y));

    initial begin
        $dumpfile("task3_tb.vcd");
        $dumpvars(0, tb_mul8u_fast);
        // Corner cases
        a = 0;   b = 0;   #10;
        a = 0;   b = 255; #10;
        a = 255; b = 0;   #10;
        a = 255; b = 255; #10;

        // Typical values
        a = 1;   b = 1;   #10;
        a = 7;   b = 9;   #10;
        a = 15;  b = 15;  #10;

        // Random tests
        a = 23;  b = 19;  #10;
        a = 128; b = 2;   #10;
        a = 200; b = 100; #10;

        $finish;
    end

endmodule

task3_tb.vcd
$date
	Fri Feb 20 09:39:50 2026
$end
$version
	Icarus Verilog
$end
$timescale
	1s
$end
$scope module tb_mul8u_fast $end
$var wire 16 ! y [15:0] $end
$var reg 8 " a [7:0] $end
$var reg 8 # b [7:0] $end
$scope module DUT $end
$var wire 8 $ a [7:0] $end
$var wire 8 % b [7:0] $end
$var wire 16 & y [15:0] $end
$scope begin PARTIALS[0] $end
$upscope $end
$scope begin PARTIALS[1] $end
$upscope $end
$scope begin PARTIALS[2] $end
$upscope $end
$scope begin PARTIALS[3] $end
$upscope $end
$scope begin PARTIALS[4] $end
$upscope $end
$scope begin PARTIALS[5] $end
$upscope $end
$scope begin PARTIALS[6] $end
$upscope $end
$scope begin PARTIALS[7] $end
$upscope $end
$upscope $end
$upscope $end
$enddefinitions $end
#0
$dumpvars
b0 &
b0 %
b0 $
b0 #
b0 "
b0 !
$end
#10
b11111111 #
b11111111 %
#20
b0 !
b0 &
b0 #
b0 %
b11111111 "
b11111111 $
#30
b1111111000000001 !
b1111111000000001 &
b11111111 #
b11111111 %
#40
b1 !
b1 &
b1 #
b1 %
b1 "
b1 $
#50
b111111 !
b111111 &
b1001 #
b1001 %
b111 "
b111 $
#60
b11100001 !
b11100001 &
b1111 #
b1111 %
b1111 "
b1111 $
#70
b110110101 !
b110110101 &
b10011 #
b10011 %
b10111 "
b10111 $
#80
b100000000 !
b100000000 &
b10 #
b10 %
b10000000 "
b10000000 $
#90
b100111000100000 !
b100111000100000 &
b1100100 #
b1100100 %
b11001000 "
b11001000 $
